dac/__init__.py
dac/__main__.py
dac/compare/__init__.py
dac/compare/encodec.py
dac/model/__init__.py
dac/model/base.py
dac/model/dac.py
dac/model/discriminator.py
dac/nn/__init__.py
dac/nn/layers.py
dac/nn/loss.py
dac/nn/quantize.py
dac/utils/__init__.py
dac/utils/decode.py
dac/utils/encode.py
tests/__init__.py
tests/test_cli.py
tests/test_train.py
descript_audio_codec-0.0.5.dist-info/LICENSE
descript_audio_codec-0.0.5.dist-info/METADATA
descript_audio_codec-0.0.5.dist-info/WHEEL
descript_audio_codec-0.0.5.dist-info/top_level.txt
descript_audio_codec-0.0.5.dist-info/RECORD
